llm_knowledge_graph/__init__.py
llm_knowledge_graph/client.py
llm_knowledge_graph-0.1.3.dist-info/METADATA
llm_knowledge_graph-0.1.3.dist-info/WHEEL
llm_knowledge_graph-0.1.3.dist-info/entry_points.txt
llm_knowledge_graph-0.1.3.dist-info/top_level.txt
llm_knowledge_graph-0.1.3.dist-info/RECORD
